License
README.md
setup.cfg
setup.py
prentr/__init__.py
prentr/prentr.py
prentr.egg-info/PKG-INFO
prentr.egg-info/SOURCES.txt
prentr.egg-info/dependency_links.txt
prentr.egg-info/top_level.txt