Metadata-Version: 2.1
Name: prentr
Version: 0.0.1
Summary: A tool made for the brave and the lazy alike, some say it's a super tool, while others just can't withstand it's humongous powers.
Home-page: https://github.com/DmarZX2/prentr
Author: Hamad Alafefi
Author-email: hamad@alafeefi.com
License: The Unlicense
Keywords: python
Platform: UNKNOWN
License-File: License
